MANIFEST.in
setup.py
ajnwordcloud/__init__.py
ajnwordcloud/colours.py
ajnwordcloud/core.py
ajnwordcloud/data.py
ajnwordcloud/fonts.py
ajnwordcloud/ii_search.c
ajnwordcloud/mask_images.py
ajnwordcloud.egg-info/PKG-INFO
ajnwordcloud.egg-info/SOURCES.txt
ajnwordcloud.egg-info/dependency_links.txt
ajnwordcloud.egg-info/not-zip-safe
ajnwordcloud.egg-info/requires.txt
ajnwordcloud.egg-info/top_level.txt
ajnwordcloud/font/Chunkfive.otf
ajnwordcloud/font/LICENSE_xkcd.txt
ajnwordcloud/font/MouseMemoirs.ttf
ajnwordcloud/font/OFL_MouseMemoirs.txt
ajnwordcloud/font/SIL Open Font License_Chunkfive.txt
ajnwordcloud/font/xkcd.otf
ajnwordcloud/mask_image/alien.png
ajnwordcloud/mask_image/circle.png
ajnwordcloud/mask_image/cloud.png
ajnwordcloud/mask_image/heart.png
ajnwordcloud/mask_image/roundrect.png
ajnwordcloud/mask_image/speech.png
ajnwordcloud/mask_image/star5.png
ajnwordcloud/mask_image/star6.png
ajnwordcloud/mask_image/thought.png
ajnwordcloud/mask_image/tree.png
ajnwordcloud/mask_image/uk.png
ajnwordcloud/mask_image/usa.png