Metadata-Version: 1.0
Name: ajnwordcloud
Version: 0.2.3
Summary: simple wordcloud generator
Home-page: http://github.com/voiceoftreason/ajnwordcloud
Author: Andy Newton
Author-email: voiceoftreason@me.com
License: MIT
Platform: UNKNOWN
